Metadata-Version: 2.1
Name: qtdigest
Version: 0.3.1
Summary: python implementation of Dunning's T-Digest
Home-page: https://github.com/QunarOPS/qtdigest
Author: zskymn
Author-email: zsymn@163.com
License: MIT
Platform: UNKNOWN
Classifier: Development Status :: 3 - Alpha
Classifier: Intended Audience :: Developers
Classifier: Topic :: Scientific/Engineering
Classifier: License :: OSI Approved :: MIT License
Classifier: Programming Language :: Python :: 2.7
Provides-Extra: test
